ros_license_toolkit/__init__.py
ros_license_toolkit/checks.py
ros_license_toolkit/common.py
ros_license_toolkit/copyright.py
ros_license_toolkit/license_tag.py
ros_license_toolkit/main.py
ros_license_toolkit/package.py
ros_license_toolkit/repo.py
ros_license_toolkit/ui_elements.py
ros_license_toolkit/license_checks/license_file_referenced_check.py
ros_license_toolkit/license_checks/license_in_code_check.py
ros_license_toolkit/license_checks/license_tag_exists_check.py
ros_license_toolkit/license_checks/license_tag_is_spdx.py
ros_license_toolkit/license_checks/license_text_exists_check.py
ros_license_toolkit/license_checks/schema_check.py
ros_license_toolkit-2.0.2.dist-info/licenses/LICENSE
ros_license_toolkit-2.0.2.dist-info/licenses/NOTICE
ros_license_toolkit-2.0.2.dist-info/METADATA
ros_license_toolkit-2.0.2.dist-info/WHEEL
ros_license_toolkit-2.0.2.dist-info/entry_points.txt
ros_license_toolkit-2.0.2.dist-info/top_level.txt
ros_license_toolkit-2.0.2.dist-info/RECORD
