Metadata-Version: 2.4
Name: ros_license_toolkit
Version: 2.0.2
Summary: Checks ROS packages for correct license declaration.
Author-email: Christian Henkel <christian.henkel2@de.bosch.com>
License: 
Project-URL: homepage, https://github.com/boschresearch/ros_license_toolkit
Project-URL: repository, https://github.com/boschresearch/ros_license_toolkit
Keywords: ros,license,toolkit,oss,packages
Classifier: License :: OSI Approved :: Apache Software License
Classifier: Programming Language :: Python :: 3
Classifier: Programming Language :: Python :: 3.7
Classifier: Programming Language :: Python :: 3.8
Classifier: Programming Language :: Python :: 3.9
Classifier: Programming Language :: Python :: 3.10
Classifier: Programming Language :: Python :: 3.11
Classifier: Framework :: Robot Framework :: Tool
Classifier: Topic :: Software Development :: Quality Assurance
Classifier: Topic :: Software Development :: Libraries :: Python Modules
Requires-Python: >=3.7
License-File: LICENSE
License-File: NOTICE
Requires-Dist: gitpython
Requires-Dist: rospkg
Requires-Dist: scancode-toolkit>=32.0.8
Requires-Dist: requests
Requires-Dist: python-Levenshtein
Provides-Extra: dev
Requires-Dist: pytest; extra == "dev"
Requires-Dist: pytest-cov; extra == "dev"
Requires-Dist: pycodestyle; extra == "dev"
Requires-Dist: flake8; extra == "dev"
Requires-Dist: mypy; extra == "dev"
Requires-Dist: isort; extra == "dev"
Requires-Dist: bumpver; extra == "dev"
Dynamic: license-file
